{
    "ISBN": 9784873118369,
    "タイトル": "ゼロから作るDeep Learning 2",
    "サブタイトル": "自然言語処理編",
    "著者": "斎藤 康毅",
    "出版社": "株式会社オーム社",
    "説明": "大ベストセラーの続編。さらに作る、さらに深くDeep Learningに迫る！\nコンピュータの専門書としては異例の大ヒットを記録した『ゼロから作るDeep Learning』の続編。第二弾の本書では、自然言語処理や時系列データ処理に焦点を当て、ディープラーニングを使ってさまざまな問題に挑みます。word2vecやRNN（リカレントニューラルネットワーク）、LSTMやGRU、seq2seqやAttention……ディープラーニングを支えるこれら最先端の技術を実装レベルでマスターできます。前作同様、平坦な言葉で分かりやすくをモットーに、高度に見える技術の裏側をじっくり説明し、実際に作ることで理解を深めます。最後までコンセプトは変わらない。ゼロから作る！",
    "言語": "jpn",
    "ページ数": "448",
    "発売日": "20180720",
    "レーベル": "Javaバイブルシリーズ",
    "値段": "",
    "画像URL": "https://cover.openbd.jp/9784873118369.jpg"
}