{
    "ISBN": 9784873117256,
    "タイトル": "CSS3開発者ガイド",
    "サブタイトル": "モダンWebデザインのスタイル設計",
    "著者": "牧野 聡",
    "出版社": "株式会社オーム社",
    "説明": "CSS3の最新技術動向を知る！\n世界的ベストセラー書“The Book of CSS3”待望の邦訳。本書では難解なCSS3仕様を平易な言葉で解説し、一般に広く使われているモダンなブラウザとCSS3で何ができるかを明らかにしながら数年先を見越した最先端のWebデザインを追求します。良いデザインの原則に焦点を当て、実践的なサンプルを豊富に使って解説しているので、読者は無理なくCSSのスキルを向上できます。ウェブ開発の中でスタイルを設計しながらどんなデザインにしてやろうかと考える開発者は必読。気絶するほど美しいリッチなウェブを作れるようになります。うまく魅せないCSSなんてCSSじゃない！",
    "言語": "jpn",
    "ページ数": "352",
    "発売日": "20150703",
    "レーベル": "できるPRO",
    "値段": "",
    "画像URL": "https://cover.openbd.jp/9784844365129.jpg"
}