{
    "ISBN": 9784845918270,
    "タイトル": "デザインの知恵",
    "サブタイトル": "情報デザインから社会のかたちづくりへ",
    "著者": "須永剛司",
    "出版社": "日経ＢＰマーケティング",
    "説明": "多くのデザイナーに影響を与えてきた\n情報デザイン分野の第一人者が、\n30年にわたる経験と実例から、\nそのデザイン哲学、\nこれからのデザインの可能性を語る\n\n須永先生の授業に出会えなければ、\nいまの僕は存在しなかっただろう。\n――水野学［good design company］\n\n\n\n多摩美術大学に情報デザイン学科をつくり、日本の美大に「情報デザイン」という概念を定着させ、これまで数多くのデザイナーを育ててきた須永剛司。\n\n本書では、「デザインとは何か」という根源的な問いかけから出発し、自身の思考の歩みや教育現場での実践を再考察しながら、現代の情報デザインの課題、人間のためのデザインのあり方を論じていく。\n\n目に見えない情報の時空にかたちを与える「情報デザイン」。その試みを続けてきたからこそわかったデザインのおもしろさ、デザインの知恵を使うことで人々が自発的に社会をかたちづくっていけることの気づきなど、第一人者ならではの視点から、かつてない伸びやかで多角的なデザイン論が展開される。人間とデザイン、社会とデザインのあり方を考え、デザインの可能性を問い直すための優しさとヒントに満ちた一冊。",
    "言語": "jpn",
    "ページ数": 291,
    "発売日": "20190426",
    "レーベル": "Javaバイブルシリーズ",
    "値段": "",
    "画像URL": "https://cover.openbd.jp/9784845918270.jpg"
}