{
    "ISBN": 9784798049250,
    "タイトル": "ランディングページの教科書　売上をガンガンあげるWeb制作8つのコツ",
    "サブタイトル": "基礎知識から、環境構築、ライブラリの活用法まで!",
    "著者": "あびるやすみつ",
    "出版社": "秀和システム",
    "説明": "「見栄えがいいデザインはできるけれど、売れるデザインはわからない」\n　「売れるページを作れるようになって制作単価を上げたい」\n　「勉強すべき分野が多岐にわたりすぎていて、多数の本を読むには腰が重い」\n　このような悩みをお持ちではないでしょうか？\n　この本は、そんなWebデザイナーのあなたに向けて作りました。\n\n　ランディングページとは、検索結果やWeb広告をクリックした際に表示される、特定の商品・サービスを売るための縦に長い1枚のWebページのことです。この本では、その作り方や、活用の仕方を説明しています。\n　単品リピート系商材に強いネット広告コンサルタントの「加藤公一レオ」さん。\n　SEO・コンテンツマーケティング専門家の「松尾茂起」さん\n　運用型広告専門家の「阿部圭司」さん。\n　会計事務所のWeb集客とWeb採用の専門家の「榎本元」さん。\n　そしてアフィリエイト・独自ドメイン多品種通販専門家であり著者の「あびるやすみつ」。\n　この本は、そうした5人の専門家が持つノウハウから「特に重要！」というものをまとめたキュレーション本です。勉強しだしたら範囲がとてつもなく広くなってしまうWeb担当者が、サクっと「売るためのWeb戦略」を理解することができるように、という狙いで構成しています。\n\n　この本を読んで実行すると、あなたはこうなります。\n\n・「売れるWebデザイン」のつくり方がわかります。\n・クライアントから「あなたの制作料金は高いけど、売れるサイトを作ってもらえるから、ぜひ依頼したい」と言ってもらえるようになります。\n・なんと仕事がなくても自力で稼げるようになります。\n\n　この本を読んで、ぜひそのようなWebデザイナーになりましょう！\n",
    "言語": "jpn",
    "ページ数": "208",
    "発売日": "20171020",
    "レーベル": "KS情報科学専門書",
    "値段": "",
    "画像URL": "https://cover.openbd.jp/9784798049250.jpg"
}