{
    "ISBN": 9784416618851,
    "タイトル": "動物デッサンテクニック",
    "サブタイトル": "骨格からプロポーションのとらえ方まで徹底解説",
    "著者": "岡本 泰子",
    "出版社": "誠文堂新光社",
    "説明": "動物の「らしさ」を表現するには実際に動物を観察するのが一番ですが、\n骨格や筋肉のつき方、プロポーションなどの基礎知識を理解する事で、\nより早く的確に形を捉えることが出来るようになります。\n\nこれは著者のもう一つの専門分野である、古生物の化石を復元する際に断片的な情報に\n生命の「らしさ」を吹き込む手助けとなっています。\n当時の姿を「生き生きと」表現するために\n著者がサイエンティフィックイラストレーション（復元画）の世界で培ってきた経験をもとに、\n動物デッサン（スケッチ）の基礎知識や、「らしさ」を表現するために必要なテクニックを\n徹底解説します。\n\n骨格を知るために博物館へ足を運び、動物園で動きをとらえる。\n代表的な動物は全身骨格図、筋肉図を交えて解説。\n作例として身近な動物である犬、猫、鳥などから、ハリネズミ、フクロウ、カワウソ、\nパンダなど近年人気の動物を始め、大型哺乳類や爬虫類など多種多様な生物を、\nクロッキーやスケッチ作品で収録しました。\n\nデザイン系の学生に限らず、ペットの愛らしい姿を描きたい方、漫画家を目指す方、\nまたはキャラクターデザインを志す方にも、必須の参考書となるでしょう。\n\n■目次\nprologue\n紙色を生かして描く／大好きな動物を描く／ペットのポートレート／かわいいしぐさを描く／ペットを観察して描く\n1章：画材と使い方\n使いやすい画材と道具／画材を使い分ける／ドローイングの基礎練習\n2章：生態を理解する\n博物館へ行こう！／動物園へ行こう！／形と動きをとらえよう／パーツを比べよう\n3章：身近な動物を描く\nイヌ／ネコ／ウマ／ウシ・ヤギ・ヒツジ／ブタ／ラクダ・アルパカ／ネズミ・リス・ウサギ／トリ\n4章：野生動物を描く\n食肉目（イヌのなかま・ネコのなかま・ウマのなかま）／奇蹄目／長鼻目／水棲の哺乳類／霊長目／有袋類／特殊な哺乳類／鳥類／両生類・爬虫類",
    "言語": "jpn",
    "ページ数": "192",
    "発売日": "20180910",
    "レーベル": "デッサンを極める！",
    "値段": "",
    "画像URL": "https://cover.openbd.jp/9784416618851.jpg"
}