{
    "ISBN": 9784485600368,
    "タイトル": "機械学習の本",
    "サブタイトル": "CPU,I/Oからセンサ,LEDまで無駄なく確実に動かす",
    "著者": "北村 拓也",
    "出版社": "ＣＱ出版",
    "説明": "本書は、機械学習の定義から専門的な内容、将来展望までを把握するために、3編に渡って記述しました。\n機械学習は人工知能技術の機能のひとつで、イコールではありません。近年、計算機技術の向上と深層学習アルゴリズムの確立により、実用性が高まり、ブームが到来しているといえます。ただ、機械学習が何なのかということを理解している方々が少ないのが現状です。\n本書は「興味があるが、よくわからない」、「数学が苦手でやりたいけど、一歩踏み出せない」という方々に対し、理解してもらえる書籍です。",
    "言語": "jpn",
    "ページ数": 148,
    "発売日": "20180718",
    "レーベル": "スッキリ！がってん！",
    "値段": "",
    "画像URL": "https://cover.openbd.jp/9784789845281.jpg"
}