{
    "ISBN": 9784886476388,
    "タイトル": "HTML演習 HTML5版",
    "サブタイトル": "標準ライブラリでゼロからWebアプリを作る",
    "著者": "中島　省吾",
    "出版社": "エスシーシー",
    "説明": "▼「はじめに」より\n本書は、Webページの基礎技術であるHTMLの最新バージョン「HTML5」、CSS の最新バージョン「CSS3」、そして「JavaScript」について、基礎を解説しています。\nこれら、最新の技術を理解する早道は、実際にコードをエディタで入力し、ブラウザに表示してみることです。\n本書では、単に解説を読むだけではなく、同時に自分で試してみることができるように構成されています。\nすなわち、解説の中で登場する数多くのソースコードを実際に入力して表示させながら説明を読むことで、いっそう理解を深めることができます。\n加えて、 確認問題と演習問題の繰り返しによって、さらなる経験を積むことができます。\n\n本書の直接の目標は、「HTML5のソースコードを見て、記述されている内容が理解できる」ことです。\n「HTML5」が理解できるようになれば、最新のWebページを応用して自前のページを作成することも夢ではなくなります。",
    "言語": "jpn",
    "ページ数": "331",
    "発売日": "20170321",
    "レーベル": "Javaバイブルシリーズ",
    "値段": "",
    "画像URL": "https://cover.openbd.jp/9784886476388.jpg"
}