{
    "ISBN": 9784865940404,
    "タイトル": "ブロックチェーン 仕組みと理論　　サンプルで学ぶFinTechのコア技術",
    "サブタイトル": "ポスト人間中心デザインへ向けて読むべき24のテキスト",
    "著者": "愛敬真生　編著",
    "出版社": "リックテレコム",
    "説明": "◆◆金融分野に止まらない広汎な応用例を列挙◆◆\n\n本書は主にITエンジニアを対象とし、3部構成となっています。\n■基礎編（1～5章）では「ブロックチェーン＝金融」というイメージを払拭します。\nまずはビットコインとの混同を解き、技術の概要と意義、登場の背景をざっくり説明します。\nまた、金融機関をはじめ各国政府機関や企業間の実証実験、応用事例等を通じて、\n各業界の動向を紹介します。\n\n■理論編（6～10章）では、ブロックチェーンの構成要素であるP2Pネットワーク、\nコンセンサスアルゴリズム、電子署名およびハッシュ暗号を解説します。\nこれら既存技術によって解決されたことと、まだ解決されていない問題を明らかにし、\nブロックチェーン技術を利用する上での課題を考察します。\n\n■実践編（11～14章）では、代表的な3つのブロックチェーン基盤、すなわち\nBitcoin Core、Ethereum、HyperLedger Fabricを動かしてみます。\n実行環境を構築して、暗号通貨による送金やマイニングを実行するほか、\n簡単なサンプルアプリケーションを作成します。\nこれらの作業を通じ、スマートコントラクトの開発方法、各ブロックチェーン基盤の\n特徴や違いについて理解を深めます。\n",
    "言語": "jpn",
    "ページ数": "256",
    "発売日": "20161018",
    "レーベル": "IT Text",
    "値段": "",
    "画像URL": "https://cover.openbd.jp/9784865940404.jpg"
}