{
    "ISBN": 9784873117003,
    "タイトル": "データ分析によるネットワークセキュリティ",
    "サブタイトル": "人工知能の最新動向を基礎から学ぶ",
    "著者": "木下 哲也",
    "出版社": "株式会社オーム社",
    "説明": "データ分析という新しいアプローチによるセキュリティ手法を解説！\n従来の侵入検知やログファイル解析といった手法では、ネットワークのセキュリティを確保するのが不十分であるとの認識から、さまざまなデータを集めて多方面から多元的に分析した上で、適切な対策を講じようという、いままでになかった視点で書かれた画期的な内容です。順序立って理解し、系統立ったセキュリティ手法を身に付けることにより、場当たり的な対策ではなく継続的・計画的なセキュリティ対策を取ることが可能となります。",
    "言語": "jpn",
    "ページ数": "376",
    "発売日": "20160611",
    "レーベル": "「Yahoo!黒帯エンジニア」シリーズ",
    "値段": "",
    "画像URL": "https://cover.openbd.jp/9784797387605.jpg"
}