{
    "ISBN": 9784797384260,
    "タイトル": "ゲームアプリの数学",
    "サブタイトル": "Unityで学ぶ基礎からシェーダーまで",
    "著者": "久富木 隆一",
    "出版社": "翔泳社",
    "説明": "ゲームアプリの開発に必要な数学をこの一冊で！ Unityによるサンプルプログラムを実際に動かすことで、数式がどのようにゲームのグラフィックスに適用されるか、直感的に理解できます。\n\nまた数学の基本のみならず、\n・OpenGL ES 3.2の3Dグラフィックスパイプライン\n・GPUアーキテクチャー\n・iOS/Androidスマートフォン向け最適化\nなども解説。プロのスマホゲーム開発者にとっても有益な一冊です。\n",
    "言語": "jpn",
    "ページ数": "312",
    "発売日": "20150924",
    "レーベル": "ほんきで学ぶ",
    "値段": "",
    "画像URL": "https://cover.openbd.jp/9784797384260.jpg"
}