{
    "ISBN": 9784845918058,
    "タイトル": "イラストでわかる映画の歴史",
    "サブタイトル": "オフラインのない時代に生き残る",
    "著者": "細谷由依子",
    "出版社": "商事法務",
    "説明": "映画の起源は洞窟にあった!?\n\"世界のクロサワ\"は何が評価された!?\n\nカメラが発明される前、セットが生まれる前、\nハリウッドができあがる前…そこに光があった。\n\nポップなイラストで中高生から大人まで楽しめる、\n知識ゼロから学べる映画の教科書が登場！\n\n\n\n長い人類史において「映画」が生まれ、\n発展したのはこの100年ちょっとのこと。\n\n今や全国数多くの映画館や動画配信サービスの発展等で、\n手軽に作品にふれることが出来る時代になりました。\n\nこの本は、映画がどのようにつくられてきたかを\n「人」「テクノロジー（技術）」「テクニック（撮影技法）」の面から\nイラストで分かりやすく解説。\n\n遥か昔、洞窟に画を投影した時代から、\n□1890年代のエジソン、リュミエール兄弟の世紀的発明\n□1930年代『風と共に去りぬ』『オズの魔法使い』\n□50年代 サムライの美学＆ヌーヴェルヴァーグ\n□70年代 『スターウォーズ』\n□80年代 CGの登場\n□2010年代 マーヴェル・スタジオ／『マッドマックス 怒りのデス・ロード』\n□未来におけるVR、仮想現実\nなど、全部で35項目を紹介。\n\n用語集や映画製作チームの職業別解説なども収録し、\n思わず人にに喋りたくなる情報が満載です！",
    "言語": "jpn",
    "ページ数": "104",
    "発売日": "20181123",
    "レーベル": "なっとくシリーズ",
    "値段": "",
    "画像URL": "https://cover.openbd.jp/9784845918058.jpg"
}